synonym/__init__.py
synonym/extractor.py
synonym_extractor-0.1.1.dist-info/DESCRIPTION.rst
synonym_extractor-0.1.1.dist-info/METADATA
synonym_extractor-0.1.1.dist-info/RECORD
synonym_extractor-0.1.1.dist-info/WHEEL
synonym_extractor-0.1.1.dist-info/metadata.json
synonym_extractor-0.1.1.dist-info/top_level.txt
