Metadata-Version: 2.0
Name: synonym-extractor
Version: 0.1.1
Summary: Extract synonyms from sentences using Aho Corasick algorithm
Home-page: http://github.com/vi3k6i5/synonym-extractor
Author: Vikash Singh
Author-email: vikash.duliajan@gmail.com
License: UNKNOWN
Platform: any
Classifier: Programming Language :: Python
Classifier: Programming Language :: Python :: 2
Classifier: Programming Language :: Python :: 2.6
Classifier: Programming Language :: Python :: 2.7
Classifier: Programming Language :: Python :: 3.5
Classifier: Operating System :: OS Independent
Classifier: Intended Audience :: Developers
Classifier: License :: OSI Approved :: MIT License
